discordbot/__init__.py
discordbot/bot.py
discordbot/cache.py
discordbot/error.py
discordbot/event.py
discordbot/intent.py
discordbot/log_severity.py
discordbot/util.py
discordbot/api/__init__.py
discordbot/api/opcode.py
discordbot/api/payload.py
discordbot/api/status_code.py
discordbot/api/structure.py
discordbot_sync-1.2.2.dist-info/LICENSE
discordbot_sync-1.2.2.dist-info/METADATA
discordbot_sync-1.2.2.dist-info/WHEEL
discordbot_sync-1.2.2.dist-info/top_level.txt
discordbot_sync-1.2.2.dist-info/RECORD
