Metadata-Version: 2.1
Name: discordbot-sync
Version: 1.2.2
Summary: A wrapper for the Discord API that doesn't require you to use asyncio
Home-page: https://github.com/GabeMillikan/discordbot-sync
Author: gabemillikan
License: UNKNOWN
Project-URL: Bug Tracker, https://github.com/GabeMillikan/discordbot-sync/issues
Platform: UNKNOWN
Classifier: Programming Language :: Python :: 3
Classifier: License :: OSI Approved :: GNU General Public License v3 (GPLv3)
Classifier: Operating System :: OS Independent
Requires-Python: >=3.6
License-File: LICENSE
Requires-Dist: websockets
Requires-Dist: requests
Requires-Dist: psutil
